ArconaiAudio/__init__.py
ArconaiAudio/cache.py
ArconaiAudio/cli.py
ArconaiAudio/driver.py
ArconaiAudio/extract.py
ArconaiAudio/play.py
ArconaiAudio/prompt.py
ArconaiAudio-1.1.2.dist-info/METADATA
ArconaiAudio-1.1.2.dist-info/WHEEL
ArconaiAudio-1.1.2.dist-info/entry_points.txt
ArconaiAudio-1.1.2.dist-info/top_level.txt
ArconaiAudio-1.1.2.dist-info/RECORD
