Metadata-Version: 2.1
Name: ArconaiAudio
Version: 1.1.2
Summary: Downloads and unzips chromedriver to curent directory
Home-page: https://github.com/joeyism/ArconaiAudio
Author: joeyism
Author-email: joeyism101@gmail.com
License: UNKNOWN
Download-URL: https://github.com/joeyism/ArconaiAudio1.1.2.tar.gz
Platform: UNKNOWN
Requires-Dist: selenium
Requires-Dist: jsbeautifier
Requires-Dist: python-mpv
Requires-Dist: tqdm
Requires-Dist: autochromedriver
Requires-Dist: requests
Requires-Dist: inquirer (==2.5.1)
Requires-Dist: prompt-toolkit (==2.0.9)
